{"assets":{"A8D440F7540EB6085D2745254B89E234":{"type":"texture","index":13,"assetRequest":{"type":"slide","state":"incoming","slide":"953DCCF1-FB1A-47AF-BFA5-6EBD074A6F44"},"url":"global/shared.pdf","width":1024,"height":768},"D654A9C14FBE3E5AD1841544F790B9DF":{"type":"texture","index":12,"assetRequest":{"type":"slide","state":"outgoing","slide":"91193F4B-24C9-4B3A-861C-4F186A95E6D7"},"url":"global/shared.pdf","width":1024,"height":768}},"events":[{"effects":[{"beginTime":0,"baseLayer":{"animations":[],"initialState":{"affineTransform":[1,0,0,1,0,0],"masksToBounds":false,"rotation":0,"scale":1,"position":{"pointX":512,"pointY":384},"width":1024,"sublayerTransform":[1,0,0,0,0,1,0,0,0,0,1,0,0,0,0,1],"contentsRect":{"y":0,"x":0,"width":1,"height":1},"opacity":1,"edgeAntialiasingMask":251658240,"height":768,"hidden":false,"anchorPoint":{"pointX":0.5,"pointY":0.5}},"objectID":"0","layers":[{"animations":[],"initialState":{"affineTransform":[1,0,0,1,0,0],"masksToBounds":false,"rotation":0,"scale":1,"position":{"pointX":512,"pointY":384},"width":1024,"sublayerTransform":[1,0,0,0,0,1,0,0,0,0,1,-0.0004922987690640373,0,0,0,1],"contentsRect":{"y":0,"x":0,"width":1,"height":1},"opacity":1,"edgeAntialiasingMask":251658240,"height":768,"hidden":false,"anchorPoint":{"pointX":0.5,"pointY":0.5}},"layers":[{"animations":[],"layers":[],"initialState":{"affineTransform":[1,0,0,1,0,0],"masksToBounds":false,"rotation":0,"scale":1,"position":{"pointX":512,"pointY":384},"width":1024,"sublayerTransform":[1,0,0,0,0,1,0,0,0,0,1,0,0,0,0,1],"contentsRect":{"y":0,"x":0,"width":1,"height":1},"opacity":1,"edgeAntialiasingMask":0,"height":768,"hidden":false,"anchorPoint":{"pointX":0.5,"pointY":0.5}},"texture":"A8D440F7540EB6085D2745254B89E234"},{"animations":[{"timeOffset":0,"from":{"scalar":false},"beginTime":0,"repeatCount":0,"fillMode":"both","property":"hidden","autoreverses":false,"duration":0.01,"to":{"scalar":true}}],"layers":[],"initialState":{"affineTransform":[1,0,0,1,0,0],"masksToBounds":false,"rotation":0,"scale":1,"position":{"pointX":512,"pointY":384},"width":1024,"sublayerTransform":[1,0,0,0,0,1,0,0,0,0,1,0,0,0,0,1],"contentsRect":{"y":0,"x":0,"width":1,"height":1},"opacity":1,"edgeAntialiasingMask":0,"height":768,"hidden":false,"anchorPoint":{"pointX":0.5,"pointY":0.5}},"texture":"D654A9C14FBE3E5AD1841544F790B9DF"}]}]},"effects":[],"duration":0.01,"type":"transition","name":"none","objectID":"0"}],"automaticPlay":false,"hyperlinks":[],"accessibility":[{"text":"Lesson 4","targetRectangle":{"y":39,"x":79,"width":191.634,"height":61}},{"text":"pasted-image.pdf","targetRectangle":{"y":664,"x":948.5918579101562,"width":29.9375,"height":57.9375}},{"text":"Logical Operators: Checking This AND That","targetRectangle":{"y":129,"x":79,"width":357.26,"height":26.40000104904175}},{"text":"        for i in 1...7 {","targetRectangle":{"y":155.4000010490417,"x":79,"width":135.1,"height":26.40000104904175}},{"text":"            moveForward()","targetRectangle":{"y":181.8000020980835,"x":79,"width":181.8199999999999,"height":26.40000104904175}},{"text":"            if isOnGem && isBlockedLeft {","targetRectangle":{"y":208.2000031471252,"x":79,"width":298.62,"height":26.40000104904175}},{"text":"                turnRight","targetRectangle":{"y":234.600004196167,"x":79,"width":154.8,"height":26.40000104904175}},{"text":"                moveForward()","targetRectangle":{"y":261.0000052452087,"x":79,"width":201.18,"height":26.40000104904175}},{"text":"                moveForward()","targetRectangle":{"y":287.4000062942505,"x":79,"width":201.18,"height":26.40000104904175}},{"text":"                collectGem()","targetRectangle":{"y":313.8000073432922,"x":79,"width":180.66,"height":26.40000104904175}},{"text":"                turnLeft()","targetRectangle":{"y":340.200008392334,"x":79,"width":153.54,"height":26.40000104904175}},{"text":"                turnLeft()","targetRectangle":{"y":366.6000094413757,"x":79,"width":153.54,"height":26.40000104904175}},{"text":"                moveForward()","targetRectangle":{"y":393.0000104904175,"x":79,"width":201.18,"height":26.40000104904175}},{"text":"                moveForward()","targetRectangle":{"y":419.4000115394592,"x":79,"width":201.18,"height":26.40000104904175}},{"text":"                turnRight()","targetRectangle":{"y":445.800012588501,"x":79,"width":165.88,"height":26.40000104904175}},{"text":"            } else if isOnGem {","targetRectangle":{"y":472.2000136375427,"x":79,"width":205.26,"height":26.40000104904175}},{"text":"                collectGem()","targetRectangle":{"y":498.6000146865845,"x":79,"width":180.66,"height":26.40000104904175}},{"text":"                moveForward()","targetRectangle":{"y":525.0000157356262,"x":79,"width":201.18,"height":26.40000104904175}},{"text":"            }","targetRectangle":{"y":551.400016784668,"x":79,"width":63.62,"height":26.40000104904175}},{"text":"Logical Operators: Checking This OR That","targetRectangle":{"y":129,"x":544.8862307993331,"width":343.2,"height":26.40000104904175}},{"text":"for i in 1...12 {","targetRectangle":{"y":155.4000010490417,"x":544.8862307993331,"width":101.64,"height":26.40000104904175}},{"text":"    if isBlocked || isBlockedLeft {","targetRectangle":{"y":181.8000020980835,"x":544.8862307993331,"width":246.98,"height":26.40000104904175}},{"text":"        turnRight()","targetRectangle":{"y":208.2000031471252,"x":544.8862307993331,"width":127.16,"height":26.40000104904175}},{"text":"        moveForward()","targetRectangle":{"y":234.600004196167,"x":544.8862307993331,"width":162.4599999999999,"height":26.40000104904175}},{"text":"    } else {","targetRectangle":{"y":261.0000052452087,"x":544.8862307993331,"width":71.74000000000001,"height":26.40000104904175}},{"text":"        moveForward()","targetRectangle":{"y":287.4000062942505,"x":544.8862307993331,"width":162.4599999999999,"height":26.40000104904175}},{"text":"    }","targetRectangle":{"y":313.8000073432922,"x":544.8862307993331,"width":24.89999999999998,"height":26.40000104904175}}],"baseLayer":{"animations":[],"initialState":{"affineTransform":[1,0,0,1,0,0],"masksToBounds":false,"rotation":0,"scale":1,"position":{"pointX":512,"pointY":384},"width":1024,"sublayerTransform":[1,0,0,0,0,1,0,0,0,0,1,0,0,0,0,1],"contentsRect":{"y":0,"x":0,"width":1,"height":1},"opacity":1,"edgeAntialiasingMask":251658240,"height":768,"hidden":false,"anchorPoint":{"pointX":0.5,"pointY":0.5}},"objectID":"0","layers":[{"animations":[],"initialState":{"affineTransform":[1,0,0,1,0,0],"masksToBounds":false,"rotation":0,"scale":1,"position":{"pointX":512,"pointY":384},"width":1024,"sublayerTransform":[1,0,0,0,0,1,0,0,0,0,1,-0.0004922987690640373,0,0,0,1],"contentsRect":{"y":0,"x":0,"width":1,"height":1},"opacity":1,"edgeAntialiasingMask":251658240,"height":768,"hidden":false,"anchorPoint":{"pointX":0.5,"pointY":0.5}},"layers":[{"animations":[],"layers":[],"initialState":{"affineTransform":[1,0,0,1,0,0],"masksToBounds":false,"rotation":0,"scale":1,"position":{"pointX":512,"pointY":384},"width":1024,"sublayerTransform":[1,0,0,0,0,1,0,0,0,0,1,0,0,0,0,1],"contentsRect":{"y":0,"x":0,"width":1,"height":1},"opacity":1,"edgeAntialiasingMask":0,"height":768,"hidden":false,"anchorPoint":{"pointX":0.5,"pointY":0.5}},"texture":"D654A9C14FBE3E5AD1841544F790B9DF"}]}]}}]}